pretix_taler/__init__.py
pretix_taler/apps.py
pretix_taler/models.py
pretix_taler/payment.py
pretix_taler/signals.py
pretix_taler/urls.py
pretix_taler/views.py
pretix_taler/locale/de/LC_MESSAGES/django.mo
pretix_taler/locale/de/LC_MESSAGES/django.po
pretix_taler/locale/de_Informal/.gitkeep
pretix_taler/locale/de_Informal/LC_MESSAGES/django.mo
pretix_taler/locale/de_Informal/LC_MESSAGES/django.po
pretix_taler/migrations/0001_initial.py
pretix_taler/migrations/__init__.py
pretix_taler/static/pretix_taler/.gitkeep
pretix_taler/static/pretix_taler/check.js
pretix_taler/static/pretix_taler/logo.svg
pretix_taler/templates/pretix_taler/.gitkeep
pretix_taler/templates/pretix_taler/checkout_confirm_render.html
pretix_taler/templates/pretix_taler/checkout_payment_form.html
pretix_taler/templates/pretix_taler/control.html
pretix_taler/templates/pretix_taler/pay.html
pretix_taler/templates/pretix_taler/pending.html
pretix_taler-1.2.0.dist-info/LICENSE
pretix_taler-1.2.0.dist-info/METADATA
pretix_taler-1.2.0.dist-info/WHEEL
pretix_taler-1.2.0.dist-info/entry_points.txt
pretix_taler-1.2.0.dist-info/top_level.txt
pretix_taler-1.2.0.dist-info/RECORD
