Metadata-Version: 2.1
Name: pretix-taler
Version: 1.2.0
Summary: Accept payments through GNU Taler, a payment system that makes privacy-friendly online transactions fast and easy.
Home-page: https://github.com/pretix/pretix-taler
Author: pretix team
Author-email: support@pretix.eu
License: Apache
License-File: LICENSE
